{
  "cities": {
    "台北市": "Taipei City",
    "新北市": "New Taipei City",
    "桃園市": "Taoyuan City",
    "新竹市": "Hsinchu City",
    "苗栗縣": "Miaoli County",
    "台中市": "Taichung City",
    "彰化縣": "Changhua County",
    "南投縣": "Nantou County",
    "雲林縣": "Yunlin County",
    "高雄市": "Kaohsiung City",
    "屏東縣": "Pingtung County",
    "宜蘭縣": "Yilan County",
    "花蓮縣": "Hualien County",
    "台東縣": "Taitung County",
    "澎湖縣": "Penghu County",
    "台南市": "Tainan City",
    "嘉義市": "Chiayi City",
    "基隆市": "Keelung City"
  },
  "districts": {
    "信義區": "Xinyi District",
    "內湖區": "Neihu District",
    "大安區": "Da’an District",
    "萬華區": "Wanhua District",
    "士林區": "Shilin District",
    "松山區": "Songshan District",
    "中正區": "Zhongzheng District",
    "板橋區": "Banqiao District",
    "三重區": "Sanchong District",
    "新莊區": "Xinzhuang District",
    "蘆洲區": "Luzhou District",
    "土城區": "Tucheng District",
    "五股區": "Wugu District",
    "中壢區": "Zhongli District",
    "桃園區": "Taoyuan District",
    "蘆竹區": "Luzhu District",
    "龜山區": "Guishan District",
    "平鎮區": "Pingzhen District",
    "東區": "East District",
    "北區": "North District",
    "苗栗市": "Miaoli City",
    "北屯區": "Beitun District",
    "大里區": "Dali District",
    "西屯區": "Xitun District",
    "后里區": "Houli District",
    "豐原區": "Fengyuan District",
    "清水區": "Qingshui District",
    "彰化市": "Changhua City",
    "南投市": "Nantou City",
    "虎尾鎮": "Huwei Township",
    "四湖鄉": "Sihu Township",
    "三民區": "Sanmin District",
    "鼓山區": "Gushan District",
    "前金區": "Qianjin District",
    "左營區": "Zuoying District",
    "新興區": "Xinxing District",
    "橋頭區": "Qiaotou District",
    "屏東市": "Pingtung City",
    "宜蘭市": "Yilan City",
    "羅東鎮": "Luodong Township",
    "花蓮市": "Hualien City",
    "東河鄉": "Donghe Township",
    "馬公市": "Magong City",
    "善化區": "Shanhua District",
    "新營區": "Xinying District"
  }
}